playground/__init__.py
playground/cli.py
playground/constants.py
playground/core/__init__.py
playground/core/configs/__init__.py
playground/core/configs/data_config_base.py
playground/core/configs/model_config_base.py
playground/core/data/__init__.py
playground/core/data/catalog.py
playground/core/data/dataset_base.py
playground/core/data/io.py
playground/core/data/parquet_dataset.py
playground/core/expcache/__init__.py
playground/core/expcache/analyzer.py
playground/core/expcache/db.py
playground/core/expcache/fs_utils.py
playground/core/expcache/hashing.py
playground/core/expcache/registry.py
playground/core/expcache/serde.py
playground/core/expcache/transformers.py
playground/core/expcache/types_.py
playground/core/s3_source/__init__.py
playground/core/s3_source/base.py
playground/core/s3_source/ml_lake.py
playground/core/s3_source/recsys.py
playground/core/tracking/__init__.py
playground/core/tracking/git_utils.py
playground/core/tracking/mlflow_track.py
sbm_exp_sdk-0.3.0.dist-info/METADATA
sbm_exp_sdk-0.3.0.dist-info/WHEEL
sbm_exp_sdk-0.3.0.dist-info/RECORD
