Metadata-Version: 2.1
Name: sbm-exp-sdk
Version: 0.3.0
Summary: playground
Author: mikhail.marin
Author-email: mikhail.marin@sbermarket.ru
Requires-Python: >=3.9,<3.11
Classifier: Programming Language :: Python :: 3
Classifier: Programming Language :: Python :: 3.9
Classifier: Programming Language :: Python :: 3.10
Requires-Dist: boto3 (==1.21.0)
Requires-Dist: diskcache (>=5.4.0,<6.0.0)
Requires-Dist: joblib
Requires-Dist: loguru (>=0.6.0,<0.7.0)
Requires-Dist: mlflow-skinny (>=1.28.0,<2.0.0)
Requires-Dist: pandas
Requires-Dist: polars
Requires-Dist: pyarrow
Requires-Dist: pygit2 (>=1.10.0,<2.0.0)
Requires-Dist: s3fs
Requires-Dist: scipy (>=1.9.1,<2.0.0)
Requires-Dist: typer[all] (>=0.6.1,<0.7.0)
